jellyfishlightspy/__init__.py
jellyfishlightspy/cache.py
jellyfishlightspy/const.py
jellyfishlightspy/controller.py
jellyfishlightspy/helpers.py
jellyfishlightspy/model.py
jellyfishlightspy/monitor.py
jellyfishlightspy/requests.py
jellyfishlightspy/validators.py
jellyfishlights_py-0.8.0.dist-info/METADATA
jellyfishlights_py-0.8.0.dist-info/WHEEL
jellyfishlights_py-0.8.0.dist-info/top_level.txt
jellyfishlights_py-0.8.0.dist-info/RECORD
