Metadata-Version: 2.1
Name: jellyfishlights-py
Version: 0.8.0
Summary: Python library for controlling Jellyfish Lights via the local network.
Home-page: https://github.com/vinenoobjelly/jellyfishlights-py
Author: Jonathan Nielsen
Author-email: jonathann@jellyfishlighting.com
Requires-Dist: websocket-client
